door_access/__init__.py
door_access/find_reader.py
door_access/loggerconf.py
door_access/rfid_reader.py
lab_door_access-0.2.0.dist-info/LICENSE
lab_door_access-0.2.0.dist-info/METADATA
lab_door_access-0.2.0.dist-info/WHEEL
lab_door_access-0.2.0.dist-info/RECORD
